{"code":0,"msg":"success","tag":"filter-equip","data":{"info":{"type":2,"map_id":"368","name":"尘归海·饕餮洞","mode":"10人普通","introduce":"饕餮洞是海龙会青龙长老黄穆的四个藏身处之一，只有青龙长老及其亲信部队能掌握其位置，是位于凶兽岛东南方的一处十分隐蔽的岩洞，周围布满暗礁，危险重重，远看有如吞海巨兽，故名“饕餮”，海寇便在此洞中驻扎，沿洞壁两侧修建了各式建筑，高低参差，一直延伸到洞外。","backgroup":"","boss_infos":[{"index":661,"icon":"https://dl.pvp.xoyo.com/prod/icons/","name":"黄穆","summary":"黄穆是海龙会青龙长老，亦是海龙会实际上的掌控者，老谋深算，城府极深，疑心颇重。出生时被父母放入小船遗弃，漂流到凶兽岛上，被海龙会上任青龙长老捡到，成为其养子。作为青龙长老的众多候选继承人被培养，练就强键的体魄。其拳法刚柔并济，有千钧之力。凭借海上劫掠的显赫功绩以及过人的谋略，除掉了其他的候选人，在上任青龙长老去世后，正式成为青龙长老，并接管海龙会。"}],"stategy_infos":[],"maps":[{"map_id":"368","mode":"10人普通","boss_index":0},{"map_id":"369","mode":"25人英雄","boss_index":0},{"map_id":"370","mode":"25人挑战","boss_index":0}]},"cat_id":"5ce756fc8f210d75b867a6cc"}}