{"code":0,"msg":"success","tag":"filter-equip","data":{"info":{"type":1,"map_id":"106","name":"法王窟","mode":"5人普通","introduce":"鼠王，蝠王乃是多年前江湖中前列的高手，当年追随血眼龙王反出明教，屠戮江湖，掀起了一场腥风血雨。\\n　　浩气盟主谢渊为了平息三大法王的恶行率众围剿，期间反而受到三法王逆袭，遭到重创，在“仁剑”穆天磊（毛毛之父）的掩护之下，才得以逃脱。\\n　　经此一役，三大法王受到重创，龙王被少林高僧击败囚禁于持国天王殿。蝠王，鼠王也从江湖上销声匿迹，实际上正隐居于白龙口法王窟内，苦心经营势力。\\n　　今次，智慧解救血眼龙王成功，并携带盗取的《易筋经》《山河社稷图》南逃，被鼠王和蝠王掩护接回到隐居之地——法王窟之中。\\n　　谢渊为追讨《山河社稷图》，日夜行军攻入法王窟内，毛毛为了追查杀父仇人的情况，也偷偷潜入法王窟，法王窟大战，一触即发……","backgroup":"","boss_infos":[{"index":130,"icon":"https://dl.pvp.xoyo.com/prod/icons/","name":"胡鞑","summary":"胡鞑自创配合白眉老鼠打洞遁走的偏门武学，威力奇大，一时纵横披靡，在教内逐渐名声见长，终成为明教护教法王之一。但其性子畏事胆小，因此虽然年龄阅历均在蝠王之上，但教内地位却不如蝠王。"},{"index":131,"icon":"https://dl.pvp.xoyo.com/prod/icons/","name":"武逸青","summary":"武逸青虽然失去双脚，却以家传机关术打造机关蝠翼，独闯奇门武功，为明教屡立奇功，终成为护教法王之一，称为“青翼蝠王”。"},{"index":132,"icon":"https://dl.pvp.xoyo.com/prod/icons/","name":"智慧","summary":"天竺十二宝树王之一。南诏王阁逻凤对他的才智非常倚重，而援救血眼龙王，取得山河社稷图这样的重任也就顺理成章的落在了他的肩上。"}],"stategy_infos":[],"maps":[{"map_id":"106","mode":"5人普通","boss_index":0},{"map_id":"115","mode":"5人英雄","boss_index":0}]},"cat_id":"5bff4ea46c074a2e7cc22cb2"}}